deskconnd/__init__.py
deskconnd/environment.py
deskconnd/components/__init__.py
deskconnd/components/_authentication.py
deskconnd/components/_discovery.py
deskconnd/components/management.py
deskconnd/database/__init__.py
deskconnd/database/base.py
deskconnd/database/controller.py
deskconnd/database/schema.py
deskconnd-0.3.dist-info/LICENSE
deskconnd-0.3.dist-info/METADATA
deskconnd-0.3.dist-info/WHEEL
deskconnd-0.3.dist-info/top_level.txt
deskconnd-0.3.dist-info/RECORD
