Metadata-Version: 2.1
Name: deskconnd
Version: 0.3
Summary: Secure, cross-platform IPC on the network.
Home-page: https://github.com/deskconn/deskconnd
Author: Omer Akram
Author-email: om26er@gmail.com
License: GNU GPL Version 3
Download-URL: https://github.com/deskconn/deskconnd/tarball/0.3
Keywords: IPC,python
Platform: UNKNOWN
Requires-Dist: appdirs
Requires-Dist: crossbar
Requires-Dist: sqlalchemy
Requires-Dist: zeroconf
